{"data":{"id":"pepe-unchained_0x36337e694b3b1eadde50101e8aa4f4fa74463aee","type":"pool","attributes":{"base_token_price_usd":"0.0000385417998438888","base_token_price_native_currency":"0.063154102515136","quote_token_price_usd":"0.00061867","quote_token_price_native_currency":"1.0","base_token_price_quote_token":"0.06315410252","quote_token_price_base_token":"15.834284079","address":"0x36337e694b3b1eadde50101e8aa4f4fa74463aee","name":"TOSH / WPEPU 1%","pool_name":"TOSH / WPEPU","pool_fee_percentage":"1","pool_created_at":"2025-07-02T16:45:35Z","fdv_usd":"38541.7998438888","market_cap_usd":null,"price_change_percentage":{"m5":"0.39","m15":"0.39","m30":"-2.24","h1":"1.65","h6":"-35.7","h24":"-23.58"},"transactions":{"m5":{"buys":1,"sells":1,"buyers":1,"sellers":1},"m15":{"buys":1,"sells":1,"buyers":1,"sellers":1},"m30":{"buys":1,"sells":3,"buyers":1,"sellers":3},"h1":{"buys":3,"sells":11,"buyers":3,"sellers":6},"h6":{"buys":201,"sells":192,"buyers":36,"sellers":32},"h24":{"buys":445,"sells":489,"buyers":66,"sellers":53}},"volume_usd":{"m5":"109.246526768","m15":"109.246526768","m30":"124.5216821549","h1":"392.9552654328","h6":"10624.7051803319","h24":"26772.8929221872"},"reserve_in_usd":"13517.445","locked_liquidity_percentage":null},"relationships":{"base_token":{"data":{"id":"pepe-unchained_0x0b52dfa17542f30f3072c53ca5061120c74d86e9","type":"token"}},"quote_token":{"data":{"id":"pepe-unchained_0xf9cf4a16d26979b929be7176bac4e7084975fcb8","type":"token"}},"dex":{"data":{"id":"pepuswap","type":"dex"}}}}}