{"data":{"id":"pepe-unchained_0x36337e694b3b1eadde50101e8aa4f4fa74463aee","type":"pool","attributes":{"base_token_price_usd":"0.0000766943434989844","base_token_price_native_currency":"0.125719772944843","quote_token_price_usd":"0.00061153","quote_token_price_native_currency":"1.0","base_token_price_quote_token":"0.1257197729","quote_token_price_base_token":"7.954198266","address":"0x36337e694b3b1eadde50101e8aa4f4fa74463aee","name":"TOSH / WPEPU 1%","pool_name":"TOSH / WPEPU","pool_fee_percentage":"1","pool_created_at":"2025-07-02T16:45:35Z","fdv_usd":"76694.3434989843","market_cap_usd":null,"price_change_percentage":{"m5":"0","m15":"0","m30":"0","h1":"-0.94","h6":"0.9","h24":"-8.22"},"transactions":{"m5":{"buys":0,"sells":0,"buyers":0,"sellers":0},"m15":{"buys":0,"sells":1,"buyers":0,"sellers":1},"m30":{"buys":0,"sells":1,"buyers":0,"sellers":1},"h1":{"buys":0,"sells":2,"buyers":0,"sellers":2},"h6":{"buys":2,"sells":4,"buyers":2,"sellers":4},"h24":{"buys":24,"sells":17,"buyers":12,"sellers":10}},"volume_usd":{"m5":"0.0","m15":"38.3471717495","m30":"38.3471717495","h1":"111.3396726344","h6":"240.6146901331","h24":"3159.9240613464"},"reserve_in_usd":"32065.4126","locked_liquidity_percentage":null},"relationships":{"base_token":{"data":{"id":"pepe-unchained_0x0b52dfa17542f30f3072c53ca5061120c74d86e9","type":"token"}},"quote_token":{"data":{"id":"pepe-unchained_0xf9cf4a16d26979b929be7176bac4e7084975fcb8","type":"token"}},"dex":{"data":{"id":"pepuswap","type":"dex"}}}}}