{"data":{"id":"pepe-unchained_0x36337e694b3b1eadde50101e8aa4f4fa74463aee","type":"pool","attributes":{"base_token_price_usd":"0.0000726552964005072","base_token_price_native_currency":"0.160593881707527","quote_token_price_usd":"0.0004523","quote_token_price_native_currency":"1.0","base_token_price_quote_token":"0.1605938817","quote_token_price_base_token":"6.226887285","address":"0x36337e694b3b1eadde50101e8aa4f4fa74463aee","name":"TOSH / WPEPU 1%","pool_name":"TOSH / WPEPU","pool_fee_percentage":"1","pool_created_at":"2025-07-02T16:45:35Z","fdv_usd":"72655.2237447035","market_cap_usd":null,"price_change_percentage":{"m5":"0","m15":"0.2","m30":"0.14","h1":"4.95","h6":"-1.07","h24":"1.58"},"transactions":{"m5":{"buys":0,"sells":0,"buyers":0,"sellers":0},"m15":{"buys":2,"sells":0,"buyers":1,"sellers":0},"m30":{"buys":3,"sells":0,"buyers":2,"sellers":0},"h1":{"buys":5,"sells":5,"buyers":3,"sellers":3},"h6":{"buys":15,"sells":10,"buyers":8,"sellers":7},"h24":{"buys":27,"sells":17,"buyers":14,"sellers":10}},"volume_usd":{"m5":"0.0","m15":"1.6837435303","m30":"4.0900164102","h1":"289.3535066702","h6":"543.0079480551","h24":"1239.227170219"},"reserve_in_usd":"14957.5756","locked_liquidity_percentage":null},"relationships":{"base_token":{"data":{"id":"pepe-unchained_0x0b52dfa17542f30f3072c53ca5061120c74d86e9","type":"token"}},"quote_token":{"data":{"id":"pepe-unchained_0xf9cf4a16d26979b929be7176bac4e7084975fcb8","type":"token"}},"dex":{"data":{"id":"pepuswap","type":"dex"}}}}}