{"data":{"id":"pepe-unchained_0x36337e694b3b1eadde50101e8aa4f4fa74463aee","type":"pool","attributes":{"base_token_price_usd":"0.0000545901524414348","base_token_price_native_currency":"0.0883585225577517","quote_token_price_usd":"0.00061794","quote_token_price_native_currency":"1.0","base_token_price_quote_token":"0.08835852256","quote_token_price_base_token":"11.317527399","address":"0x36337e694b3b1eadde50101e8aa4f4fa74463aee","name":"TOSH / WPEPU 1%","pool_name":"TOSH / WPEPU","pool_fee_percentage":"1","pool_created_at":"2025-07-02T16:45:35Z","fdv_usd":"54590.1524414347","market_cap_usd":null,"price_change_percentage":{"m5":"-0.03","m15":"-0.03","m30":"-0.39","h1":"3.57","h6":"-5.31","h24":"9.07"},"transactions":{"m5":{"buys":0,"sells":3,"buyers":0,"sellers":2},"m15":{"buys":0,"sells":3,"buyers":0,"sellers":2},"m30":{"buys":1,"sells":6,"buyers":1,"sellers":2},"h1":{"buys":2,"sells":7,"buyers":2,"sellers":3},"h6":{"buys":9,"sells":9,"buyers":5,"sellers":4},"h24":{"buys":37,"sells":50,"buyers":17,"sellers":18}},"volume_usd":{"m5":"1.9330749433","m15":"1.9330749433","m30":"314.7741739024","h1":"321.9300810648","h6":"788.8133046573","h24":"3286.0957231953"},"reserve_in_usd":"19481.3639","locked_liquidity_percentage":null},"relationships":{"base_token":{"data":{"id":"pepe-unchained_0x0b52dfa17542f30f3072c53ca5061120c74d86e9","type":"token"}},"quote_token":{"data":{"id":"pepe-unchained_0xf9cf4a16d26979b929be7176bac4e7084975fcb8","type":"token"}},"dex":{"data":{"id":"pepuswap","type":"dex"}}}}}