{"data":{"id":"pepe-unchained_0x36337e694b3b1eadde50101e8aa4f4fa74463aee","type":"pool","attributes":{"base_token_price_usd":"0.0000513762227607849","base_token_price_native_currency":"0.0648219825679892","quote_token_price_usd":"0.00079063","quote_token_price_native_currency":"1.0","base_token_price_quote_token":"0.06482198257","quote_token_price_base_token":"15.426865399","address":"0x36337e694b3b1eadde50101e8aa4f4fa74463aee","name":"TOSH / WPEPU 1%","pool_name":"TOSH / WPEPU","pool_fee_percentage":"1","pool_created_at":"2025-07-02T16:45:35Z","fdv_usd":"51376.2227607849","market_cap_usd":null,"price_change_percentage":{"m5":"0","m15":"0.57","m30":"0.57","h1":"0.57","h6":"-0.27","h24":"-5.73"},"transactions":{"m5":{"buys":1,"sells":0,"buyers":1,"sellers":0},"m15":{"buys":3,"sells":0,"buyers":1,"sellers":0},"m30":{"buys":3,"sells":0,"buyers":1,"sellers":0},"h1":{"buys":3,"sells":0,"buyers":1,"sellers":0},"h6":{"buys":22,"sells":27,"buyers":10,"sellers":8},"h24":{"buys":64,"sells":48,"buyers":21,"sellers":18}},"volume_usd":{"m5":"8.8346521156","m15":"35.5286841156","m30":"35.5286841156","h1":"35.5286841156","h6":"1994.6814324372","h24":"3751.2861223002"},"reserve_in_usd":"16391.8664","locked_liquidity_percentage":null},"relationships":{"base_token":{"data":{"id":"pepe-unchained_0x0b52dfa17542f30f3072c53ca5061120c74d86e9","type":"token"}},"quote_token":{"data":{"id":"pepe-unchained_0xf9cf4a16d26979b929be7176bac4e7084975fcb8","type":"token"}},"dex":{"data":{"id":"pepuswap","type":"dex"}}}}}